Metadata-Version: 2.4
Name: mcp-cyoda-client
Version: 0.1.4
Summary: Model Context Protocol server for Cyoda platform - enables AI assistants to interact with Cyoda's entity management, search, workflow, and deployment capabilities
Author-email: Cyoda Team <support@cyoda.io>
License-Expression: MIT
Project-URL: Homepage, https://ai.cyoda.net
Project-URL: Documentation, https://docs.cyoda.net
Project-URL: Repository, https://github.com/Cyoda-platform/quart-client-template
Project-URL: Issues, https://github.com/Cyoda-platform/quart-client-template/issues
Keywords: mcp,cyoda,model-context-protocol,ai,llm
Classifier: Development Status :: 4 - Beta
Classifier: Intended Audience :: Developers
Classifier: Programming Language :: Python :: 3
Classifier: Programming Language :: Python :: 3.10
Classifier: Programming Language :: Python :: 3.11
Classifier: Programming Language :: Python :: 3.12
Classifier: Topic :: Software Development :: Libraries :: Python Modules
Classifier: Topic :: Internet :: WWW/HTTP :: HTTP Servers
Requires-Python: >=3.10
License-File: LICENSE
Requires-Dist: fastmcp>=2.12.0
Requires-Dist: Quart>=0.19.9
Requires-Dist: Hypercorn>=0.17.3
Requires-Dist: quart-cors>=0.7.0
Requires-Dist: quart-openapi>=1.7.2
Requires-Dist: jsonschema>=4.23.0
Requires-Dist: grpcio>=1.64.1
Requires-Dist: grpcio-tools>=1.64.1
Requires-Dist: protobuf>=5.27.3
Requires-Dist: python-dotenv>=1.1.0
Requires-Dist: requests>=2.32.3
Requires-Dist: aiofiles>=24.1.0
Requires-Dist: httpx>=0.28.1
Requires-Dist: quart-schema[pydantic]>=0.21.0
Requires-Dist: PyJWT>=2.10.1
Requires-Dist: Authlib>=1.6.0
Requires-Dist: dependency_injector>=4.48.1
Requires-Dist: psutil>=7.0.0
Provides-Extra: dev
Requires-Dist: pytest==7.4.0; extra == "dev"
Requires-Dist: pytest-asyncio==0.21.0; extra == "dev"
Requires-Dist: pytest-cov==4.1.0; extra == "dev"
Requires-Dist: black==25.1.0; extra == "dev"
Requires-Dist: isort==6.0.1; extra == "dev"
Requires-Dist: mypy==1.17.1; extra == "dev"
Requires-Dist: flake8==7.1.1; extra == "dev"
Requires-Dist: flake8-pyproject>=1.2.0; extra == "dev"
Requires-Dist: bandit==1.8.6; extra == "dev"
Requires-Dist: types-aiofiles>=23.0; extra == "dev"
Requires-Dist: types-jsonschema>=4.0; extra == "dev"
Requires-Dist: types-requests>=2.0; extra == "dev"
Requires-Dist: build>=0.10; extra == "dev"
Requires-Dist: twine>=4.0; extra == "dev"
Dynamic: license-file
